{
  "project_name": "2024 년 평택시 버스정보시스템 (BIS) 구축사업",
  "agency": "NOT_FOUND",
  "purpose": "본 사업은 평택시 전역을 대상으로 버스정류장 안내단말기를 확충하고 , 운행하는 모든 버스의 정보를 시 ․ 공간의 제약 없이 버스이용자에게 제공함으로써 대중교통 서비 스의 질을 향상시키며 , 향후 인접 교통권역을 포함한 광역 버스정보시스템 구축사업의 호환성과 상호 운영성을 확보하는 실현방안 제시를 목적으로 한다 .",
  "budget": "999,494,600원",
  "contract_type": "협상",
  "deadline": "입찰당일 제출",
  "duration": "3 개 월",
  "requirements_must": "GEN_FAIL",
  "eval_items": "기술제안서:80% / 가격제안서:20%",
  "price_eval": "기술제안서 80%, 가격제안서 20% 로 배분ㆍ평가하여 고득점자부터 협상을 실시한다",
  "eligibility": "GEN_FAIL",
  "scope_area": "평택시 전역 ( 버스정보안내단말기가 설치된 주요 버스정류장 ) -평택시 모든 도로의 버스정보 제공대상 정류소 및 환승거점을 포함한 주변 인근지역",
  "center_system_functions": "GEN_FAIL",
  "quantity_change": "사업내용 (BIT 설치물량 ) 은 현장 및 교통현황조사 후 변동될 수 있으며 , 변동은 해당 분야의 예산범위 내에서만 가능하며 , 본 사업의 사업내용은 다음과 같다 .",
  "field_test_timing": "발주기관과 협의하여 제시된 평가항목, 기준 및 일정에 준하여 실시함; 단위공정이 완료되는 시점에 발주기관의 입회하에 성능평가; 단위시스템 구축이 완료되면 전반적인 성능평가를 수행",
  "objection_policy": "② 심 의결과에 대해서 제안업체에서는 이의를 제기할 수 없다 .",
  "proposal_omission": "발주기관에서는 불명확한 부분이나 누락된 사항 , 다른 제안자의 우수한 제안 등 보완필요성이 있다고 판단되는 내용을 협상대상에 포함시킬 수 있다 .",
  "subcontracting_policy": "발주기관으로부터 사전 승인을 받아야함 / 입찰 시 및 계약체결 시 별지 7호의 소프트웨어사업 하도급 계획서를 제출하여야 함",
  "failure_recovery": "장애(고장) 통보를 받은 후 12 시간 이내 수리 완료 / 72 시간 이후 동일기종 무상 교체 요구 가능",
  "warranty_period": "1 년간",
  "test_run_end": "시운전의 종 료 는 시스템 구축 목 표 를 달 성하 였 다고 ' 갑 ' 이 판단할 때 한다 ."
}